matplotlib_helpers/__init__.py
matplotlib_helpers/chart.py
matplotlib_helpers-0.1.post6.dist-info/DESCRIPTION.rst
matplotlib_helpers-0.1.post6.dist-info/METADATA
matplotlib_helpers-0.1.post6.dist-info/RECORD
matplotlib_helpers-0.1.post6.dist-info/WHEEL
matplotlib_helpers-0.1.post6.dist-info/metadata.json
matplotlib_helpers-0.1.post6.dist-info/top_level.txt
